sliceable_dict/__init__.py
sliceable_dict/core.py
sliceable_dict/lib.py
sliceable_dict-0.4.1.dist-info/LICENSE
sliceable_dict-0.4.1.dist-info/METADATA
sliceable_dict-0.4.1.dist-info/WHEEL
sliceable_dict-0.4.1.dist-info/top_level.txt
sliceable_dict-0.4.1.dist-info/RECORD
