Metadata-Version: 2.1
Name: sliceable-dict
Version: 0.4.1
Summary: Dictionary that support slicing and multiple key selection
Author-email: Bert Palm <bert.palm.home@gmail.com>
Project-URL: Homepage, https://github.com/palmb/slice-dict
Project-URL: Bug Tracker, https://github.com/palmb/slice-dict/issues
Classifier: Programming Language :: Python :: 3
Classifier: License :: OSI Approved :: GNU General Public License v3 (GPLv3)
Classifier: Operating System :: OS Independent
Requires-Python: >=3.7
License-File: LICENSE
Requires-Dist: typing-extensions
